neuromorphopy/__init__.py
neuromorphopy/api.py
neuromorphopy/cli.py
neuromorphopy/exceptions.py
neuromorphopy/query.py
neuromorphopy/io/__init__.py
neuromorphopy/io/swc.py
neuromorphopy/utils/__init__.py
neuromorphopy/utils/api_utils.py
neuromorphopy/utils/logging.py
neuromorphopy-0.3.2.dist-info/METADATA
neuromorphopy-0.3.2.dist-info/WHEEL
neuromorphopy-0.3.2.dist-info/entry_points.txt
neuromorphopy-0.3.2.dist-info/licenses/LICENSE
neuromorphopy-0.3.2.dist-info/RECORD
