Metadata-Version: 2.4
Name: neuromorphopy
Version: 0.3.2
Summary: Lightweight standalone python CLI tool for downloading neuron morphologies from the NeuroMorpho archives.
Project-URL: repository, https://github.com/kpeez/neuromorphopy
Project-URL: documentation, https://neuromorphopy.readthedocs.io/en/latest/
Author-email: Kyle Puhger <krpuhger@gmail.com>
License: MIT License
License-File: LICENSE
Keywords: morphology,neuromorpho,neurons,neuroscience
Classifier: Development Status :: 3 - Alpha
Classifier: Intended Audience :: Science/Research
Classifier: License :: OSI Approved :: MIT License
Classifier: Programming Language :: Python :: 3
Classifier: Programming Language :: Python :: 3.11
Classifier: Topic :: Scientific/Engineering :: Bio-Informatics
Classifier: Topic :: Software Development :: Libraries
Requires-Python: >=3.11
Requires-Dist: aiohttp>=3.11.18
Requires-Dist: pandas>=2.2.3
Requires-Dist: pydantic>=2.11.3
Requires-Dist: pyyaml>=6.0.2
Requires-Dist: requests>=2.32.3
Requires-Dist: tqdm>=4.67.1
Requires-Dist: typer>=0.15.2
